Metadata-Version: 1.0
Name: abso
Version: 0.1
Summary: Set root path to a specific position.
Home-page: https://github.com/nofacer/abso.git
Author: Dustni
Author-email: dustni@qq.com
License: MIT
Platform: UNKNOWN
